mytextlib/__init__.py
mytextlib/model.py
mytextlib/processing.py
mytextlib/utils.py
tests/__init__.py
tests/test_model.py
sentiment_analysis_traditional_media_data-0.1.0.dist-info/METADATA
sentiment_analysis_traditional_media_data-0.1.0.dist-info/WHEEL
sentiment_analysis_traditional_media_data-0.1.0.dist-info/top_level.txt
sentiment_analysis_traditional_media_data-0.1.0.dist-info/RECORD
